{
  "id": "62bbdf3676d4",
  "title": "마포구, 박정호 교수 초청 청년 특강…경제 나침반 제시",
  "slug": "naver-c5d68b35",
  "source": "naver",
  "sourceUrl": "https://news.tf.co.kr/read/life/2292145.htm",
  "category": "asset-management",
  "priority": 3,
  "rawSummary": "'퇴근길학교 마포자산관리스쿨' 강의는 오는 3월4일부터 4월22일까지 매주 수요일 오후 7시에 열린다. 올해 경제전망과 금융상품, 나만의 재테크 등에 대한 주제를 다룬다. 이날부터 마포구 평생학습포털에서 접수... ",
  "publishedAt": "2026-02-11T04:26:00.000Z",
  "collectedAt": "2026-02-11T09:42:43.135Z",
  "status": "raw",
  "adminSummary": null,
  "adminKeyPoints": null,
  "adminPublishedAt": null
}