{
  "id": "7771e4f0b285",
  "title": "빗썸 사태 관련 금융위원장 주재 「점검회의」",
  "slug": "fsc-29f9b144",
  "source": "fsc",
  "sourceUrl": "https://www.korea.kr/briefing/pressReleaseView.do?newsId=156743659&call_from=rsslink",
  "category": "crypto",
  "priority": 3,
  "rawSummary": "빗썸 사태 관련 금융위원장 주재 「점검회의」\n \n  \n▴ 금융위·FIU·금감원은 2.8일(일) 금융위원장 주재 점검회의를 개최, 어제 긴급 점검회의 이후 추가 피해상황 점검 및 제도 개선방안 등 논의\n  \n ▴ 금융위원장은 빗썸 뿐만 아니라 모든 거래소의 내부통제 전반을 점검하고, 적절한 내부통제 체계를 마련할 것을 지시\n \n  \n \n  \n \nI. 회의 개요\n  \n  \n \n  금융위원장은 어제 긴급 점검회의에 이어 빗썸 사태 진행상황 파악 및 제도개선 필요사항 등을 논의하기 위해 FIU·금감원과 함께 2.8일(일) 15:00 점검회의를 개최하였다.\n \n  \n \n· (일시/장소) '26.2.8.(일) 15:00, 정부서울청사\n  \n \n  \n· 참석자\n  \n \n  \n - (금융위) 이억원 위원장(주재), 사무처장, 디지털금융정책관, FIU 제도운영기획관\n  \n - (금감원) 이세훈 수석부원장, 가상자산감독국장\n  \n  \n\n\n  \n \nII. 진행 상황\n  \n  \n \n 어제 긴급 점검회의를",
  "publishedAt": "2026-02-08T15:00:00.000Z",
  "collectedAt": "2026-02-11T02:51:42.850Z",
  "status": "raw",
  "adminSummary": null,
  "adminKeyPoints": null,
  "adminPublishedAt": null
}